models/__init__.py
models/common.py
models/experimental.py
models/tf.py
models/yolo.py
utils/__init__.py
utils/activations.py
utils/augmentations.py
utils/autoanchor.py
utils/callbacks.py
utils/datasets.py
utils/downloads.py
utils/general.py
utils/loss.py
utils/metrics.py
utils/plots.py
utils/torch_utils.py
utils/aws/__init__.py
utils/aws/resume.py
utils/loggers/__init__.py
utils/loggers/wandb/__init__.py
utils/loggers/wandb/log_dataset.py
utils/loggers/wandb/sweep.py
utils/loggers/wandb/wandb_utils.py
zh_ito_yolov5-1.0.0.0.dist-info/LICENSE
zh_ito_yolov5-1.0.0.0.dist-info/METADATA
zh_ito_yolov5-1.0.0.0.dist-info/WHEEL
zh_ito_yolov5-1.0.0.0.dist-info/top_level.txt
zh_ito_yolov5-1.0.0.0.dist-info/RECORD
