Metadata-Version: 2.1
Name: zh-ito-yolov5
Version: 1.0.0.0
Summary: AI detection
Home-page: https://github.com/z-zroud/CardScript
Author: z_road
Author-email: 489469935@qq.com
License: UNKNOWN
Platform: UNKNOWN
Classifier: Programming Language :: Python :: 3
Classifier: License :: OSI Approved :: MIT License
Classifier: Operating System :: OS Independent
